setup.py
gaus_bi_distribution/Binomialdistribution.py
gaus_bi_distribution/Gaussiandistribution.py
gaus_bi_distribution/Generaldistribution.py
gaus_bi_distribution/__init__.py
gaus_bi_distribution.egg-info/PKG-INFO
gaus_bi_distribution.egg-info/SOURCES.txt
gaus_bi_distribution.egg-info/dependency_links.txt
gaus_bi_distribution.egg-info/not-zip-safe
gaus_bi_distribution.egg-info/top_level.txt